SpiderManager/__init__.py
SpiderManager/config.py
SpiderManager/run.py
SpiderManager/uwsgi.py
SpiderManager/app/__init__.py
SpiderManager/app/proxy/__init__.py
SpiderManager/app/proxy/spiderctrl.py
SpiderManager/app/proxy/contrib/__init__.py
SpiderManager/app/proxy/contrib/scrapy.py
SpiderManager/app/schedulers/__init__.py
SpiderManager/app/schedulers/common.py
SpiderManager/app/spider/__init__.py
SpiderManager/app/spider/controller.py
SpiderManager/app/spider/model.py
SpiderManager/app/static/css/AdminLTE.min.css
SpiderManager/app/static/css/app.css
SpiderManager/app/static/css/bootstrap.min.css
SpiderManager/app/static/css/bootstrap.min.css.map
SpiderManager/app/static/css/font-awesome.min.css
SpiderManager/app/static/css/ionicons.min.css
SpiderManager/app/static/css/alt/AdminLTE-without-plugins.min.css
SpiderManager/app/static/css/skins/_all-skins.min.css
SpiderManager/app/static/css/skins/skin-black-light.min.css
SpiderManager/app/static/fonts/FontAwesome.otf
SpiderManager/app/static/fonts/fontawesome-webfont.eot
SpiderManager/app/static/fonts/fontawesome-webfont.svg
SpiderManager/app/static/fonts/fontawesome-webfont.ttf
SpiderManager/app/static/fonts/fontawesome-webfont.woff
SpiderManager/app/static/fonts/fontawesome-webfont.woff2
SpiderManager/app/static/fonts/glyphicons-halflings-regular.eot
SpiderManager/app/static/fonts/glyphicons-halflings-regular.svg
SpiderManager/app/static/fonts/glyphicons-halflings-regular.ttf
SpiderManager/app/static/fonts/glyphicons-halflings-regular.woff
SpiderManager/app/static/fonts/glyphicons-halflings-regular.woff2
SpiderManager/app/static/fonts/ionicons.eot
SpiderManager/app/static/fonts/ionicons.svg
SpiderManager/app/static/fonts/ionicons.ttf
SpiderManager/app/static/fonts/ionicons.woff
SpiderManager/app/static/js/AdminLTE.min.js
SpiderManager/app/static/js/Chart.min.js
SpiderManager/app/static/js/bootstrap.min.js
SpiderManager/app/static/js/demo.js
SpiderManager/app/static/js/fastclick.min.js
SpiderManager-1.3.1.dist-info/METADATA
SpiderManager-1.3.1.dist-info/WHEEL
SpiderManager-1.3.1.dist-info/entry_points.txt
SpiderManager-1.3.1.dist-info/top_level.txt
SpiderManager-1.3.1.dist-info/RECORD
