Metadata-Version: 2.1
Name: SpiderManager
Version: 1.3.1
Summary: Admin ui for spider service
Home-page: https://github.com/koneb71/SpiderManager/
Author: koneb71
Author-email: koneb71@gmail.com
License: MIT
Platform: UNKNOWN
Classifier: Development Status :: 4 - Beta
Classifier: License :: OSI Approved :: MIT License
Classifier: Operating System :: OS Independent
Classifier: Programming Language :: Python :: 3.7
Requires-Dist: aniso8601 (==9.0.1)
Requires-Dist: APScheduler (==3.7.0)
Requires-Dist: certifi (==2021.5.30)
Requires-Dist: chardet (==4.0.0)
Requires-Dist: click (==8.0.1)
Requires-Dist: Flask (==2.0.1)
Requires-Dist: Flask-BasicAuth (==0.2.0)
Requires-Dist: Flask-RESTful (==0.3.9)
Requires-Dist: flask-restful-swagger (==0.20.1)
Requires-Dist: Flask-SQLAlchemy (==2.5.1)
Requires-Dist: greenlet (==1.1.0)
Requires-Dist: idna (==2.10)
Requires-Dist: itsdangerous (==2.0.1)
Requires-Dist: Jinja2 (==3.0.1)
Requires-Dist: MarkupSafe (==2.0.1)
Requires-Dist: PyMySQL (==1.0.2)
Requires-Dist: python-dateutil (==2.8.1)
Requires-Dist: pytz (==2021.1)
Requires-Dist: requests (==2.25.1)
Requires-Dist: six (==1.16.0)
Requires-Dist: SQLAlchemy (==1.4.17)
Requires-Dist: tzlocal (==2.1)
Requires-Dist: urllib3 (==1.26.5)
Requires-Dist: Werkzeug (==2.0.1)
